main.py
limon-0.0.1.dist-info/LICENSE
limon-0.0.1.dist-info/METADATA
limon-0.0.1.dist-info/WHEEL
limon-0.0.1.dist-info/top_level.txt
limon-0.0.1.dist-info/RECORD
